distributed_downloader/__init__.py
distributed_downloader/core/MPI_download_prep.py
distributed_downloader/core/MPI_downloader_verifier.py
distributed_downloader/core/MPI_multimedia_downloader.py
distributed_downloader/core/MPI_multimedia_downloader_controller.py
distributed_downloader/core/__about__.py
distributed_downloader/core/__init__.py
distributed_downloader/core/fake_profiler.py
distributed_downloader/core/initialization.py
distributed_downloader/core/main.py
distributed_downloader/core/utils.py
distributed_downloader/core/initializers/README.md
distributed_downloader/core/initializers/__init__.py
distributed_downloader/core/initializers/base_initializer.py
distributed_downloader/core/initializers/eol_initializer.py
distributed_downloader/core/initializers/fathom_net_initializer.py
distributed_downloader/core/initializers/gbif_initializer.py
distributed_downloader/core/initializers/lila_initializer.py
distributed_downloader/core/initializers/tol_fathomNet_initializer.py
distributed_downloader/core/initializers/tol_general_initializer.py
distributed_downloader/core/mpi_downloader/DirectWriter.py
distributed_downloader/core/mpi_downloader/Downloader.py
distributed_downloader/core/mpi_downloader/PreLoader.py
distributed_downloader/core/mpi_downloader/__init__.py
distributed_downloader/core/mpi_downloader/dataclasses.py
distributed_downloader/core/mpi_downloader/utils.py
distributed_downloader/tools/__init__.py
distributed_downloader/tools/checkpoint.py
distributed_downloader/tools/config.py
distributed_downloader/tools/filter.py
distributed_downloader/tools/filters.py
distributed_downloader/tools/main.py
distributed_downloader/tools/registry.py
distributed_downloader/tools/runner.py
distributed_downloader/tools/runners.py
distributed_downloader/tools/scheduler.py
distributed_downloader/tools/schedulers.py
distributed_downloader/tools/utils.py
distributed_downloader/tools/verification.py
distributed_downloader/tools/config_templates/downloader.yaml
distributed_downloader-0.3.0b0.dist-info/METADATA
distributed_downloader-0.3.0b0.dist-info/WHEEL
distributed_downloader-0.3.0b0.dist-info/entry_points.txt
distributed_downloader-0.3.0b0.dist-info/licenses/LICENSE
distributed_downloader-0.3.0b0.dist-info/RECORD
