Metadata-Version: 2.4
Name: distributed_downloader
Version: 0.3.0b0
Summary: MPI-based tool for downloading images from a list of URLs in parallel.
Project-URL: Homepage, https://github.com/Imageomics/distributed-downloader
Project-URL: Repository, https://github.com/Imageomics/distributed-downloader.git
Project-URL: Bug Tracker, https://github.com/Imageomics/distributed-downloader/issues
Author-email: Andrey Kopanev <kopanev.1@osu.edu>, "Elizabeth G. Campolongo" <e.campolongo479@gmail.com>, "Matthew J. Thompson" <thompson.m.j@outlook.com>
License-File: LICENSE
Classifier: Development Status :: 4 - Beta
Classifier: License :: OSI Approved :: MIT License
Classifier: Operating System :: OS Independent
Classifier: Programming Language :: Python :: 3
Classifier: Programming Language :: Python :: 3.10
Classifier: Programming Language :: Python :: 3.11
Requires-Python: <3.12,>=3.10
Requires-Dist: attrs
Requires-Dist: brotli
Requires-Dist: cramjam
Requires-Dist: cython
Requires-Dist: fsspec
Requires-Dist: inflate64
Requires-Dist: mpi4py
Requires-Dist: multivolumefile
Requires-Dist: opencv-python
Requires-Dist: pandas
Requires-Dist: pathspec
Requires-Dist: pillow
Requires-Dist: psutil
Requires-Dist: pyarrow
Requires-Dist: pybcj
Requires-Dist: pycryptodomex
Requires-Dist: pyppmd
Requires-Dist: pyspark
Requires-Dist: python-dotenv
Requires-Dist: pyyaml
Requires-Dist: pyzstd
Requires-Dist: requests
Requires-Dist: setuptools
Requires-Dist: texttable
Requires-Dist: trove-classifiers
Requires-Dist: typing-extensions
Requires-Dist: wheel
Provides-Extra: dev
Requires-Dist: pytest; extra == 'dev'
Requires-Dist: ruff; extra == 'dev'
Provides-Extra: keywords
Requires-Dist: dataset-generation; extra == 'keywords'
Requires-Dist: distributed; extra == 'keywords'
Requires-Dist: download; extra == 'keywords'
Requires-Dist: mpi-applications; extra == 'keywords'
Requires-Dist: parallel; extra == 'keywords'
Requires-Dist: url; extra == 'keywords'
